odoo/addons/sale_order_line_discount_validation/README.rst
odoo/addons/sale_order_line_discount_validation/__init__.py
odoo/addons/sale_order_line_discount_validation/__manifest__.py
odoo/addons/sale_order_line_discount_validation/data/mail_template.xml
odoo/addons/sale_order_line_discount_validation/i18n/es.po
odoo/addons/sale_order_line_discount_validation/i18n/sale_order_line_discount_validation.pot
odoo/addons/sale_order_line_discount_validation/models/__init__.py
odoo/addons/sale_order_line_discount_validation/models/res_company.py
odoo/addons/sale_order_line_discount_validation/models/res_config_settings.py
odoo/addons/sale_order_line_discount_validation/models/sale_order.py
odoo/addons/sale_order_line_discount_validation/readme/CONFIGURE.rst
odoo/addons/sale_order_line_discount_validation/readme/CONTRIBUTORS.rst
odoo/addons/sale_order_line_discount_validation/readme/DESCRIPTION.rst
odoo/addons/sale_order_line_discount_validation/readme/USAGE.rst
odoo/addons/sale_order_line_discount_validation/report/__init__.py
odoo/addons/sale_order_line_discount_validation/report/sale_report.py
odoo/addons/sale_order_line_discount_validation/static/description/icon.png
odoo/addons/sale_order_line_discount_validation/static/description/index.html
odoo/addons/sale_order_line_discount_validation/views/res_config_settings_views.xml
odoo/addons/sale_order_line_discount_validation/views/sale_order.xml
odoo14_addon_sale_order_line_discount_validation-14.0.2.0.1.dist-info/METADATA
odoo14_addon_sale_order_line_discount_validation-14.0.2.0.1.dist-info/WHEEL
odoo14_addon_sale_order_line_discount_validation-14.0.2.0.1.dist-info/top_level.txt
odoo14_addon_sale_order_line_discount_validation-14.0.2.0.1.dist-info/RECORD
